quiver_to_rst
