Metadata-Version: 1.1
Name: quiver-to-rst
Version: 0.1.2
Summary: Convert your Quiver notes into RestructuredText
Home-page: https://github.com/coddingtonbear/quiver-to-rst
Author: Adam Coddington
Author-email: me@adamcoddington.net
License: UNKNOWN
Platform: UNKNOWN
Classifier: License :: OSI Approved :: MIT License
Classifier: Operating System :: OS Independent
